MANIFEST.in
setup.py
ant_ray_nightly.egg-info/PKG-INFO
ant_ray_nightly.egg-info/SOURCES.txt
ant_ray_nightly.egg-info/dependency_links.txt
ant_ray_nightly.egg-info/entry_points.txt
ant_ray_nightly.egg-info/not-zip-safe
ant_ray_nightly.egg-info/requires.txt
ant_ray_nightly.egg-info/top_level.txt
ray/__init__.py
ray/_raylet.pyi
ray/_version.py
ray/actor.py
ray/client_builder.py
ray/cluster_utils.py
ray/cross_language.py
ray/exceptions.py
ray/job_config.py
ray/py.typed
ray/remote_function.py
ray/runtime_context.py
ray/setup-dev.py
ray/types.py
ray/_private/__init__.py
ray/_private/arrow_serialization.py
ray/_private/async_compat.py
ray/_private/async_utils.py
ray/_private/auto_init_hook.py
ray/_private/client_mode_hook.py
ray/_private/collections_utils.py
ray/_private/compat.py
ray/_private/conftest_utils.py
ray/_private/dict.py
ray/_private/external_storage.py
ray/_private/function_manager.py
ray/_private/gcs_aio_client.py
ray/_private/gcs_pubsub.py
ray/_private/gcs_utils.py
ray/_private/inspect_util.py
ray/_private/internal_api.py
ray/_private/log.py
ray/_private/log_monitor.py
ray/_private/logging_utils.py
ray/_private/memory_monitor.py
ray/_private/metrics_agent.py
ray/_private/node.py
ray/_private/parameter.py
ray/_private/process_watcher.py
ray/_private/profiling.py
ray/_private/prometheus_exporter.py
ray/_private/protobuf_compat.py
ray/_private/pydantic_compat.py
ray/_private/ray_client_microbenchmark.py
ray/_private/ray_cluster_perf.py
ray/_private/ray_constants.py
ray/_private/ray_experimental_perf.py
ray/_private/ray_microbenchmark_helpers.py
ray/_private/ray_option_utils.py
ray/_private/ray_perf.py
ray/_private/ray_process_reaper.py
ray/_private/resource_spec.py
ray/_private/serialization.py
ray/_private/services.py
ray/_private/signature.py
ray/_private/state.py
ray/_private/state_api_test_utils.py
ray/_private/storage.py
ray/_private/test_utils.py
ray/_private/tls_utils.py
ray/_private/utils.py
ray/_private/worker.py
ray/_private/accelerators/__init__.py
ray/_private/accelerators/accelerator.py
ray/_private/accelerators/amd_gpu.py
ray/_private/accelerators/hpu.py
ray/_private/accelerators/intel_gpu.py
ray/_private/accelerators/neuron.py
ray/_private/accelerators/npu.py
ray/_private/accelerators/nvidia_gpu.py
